adafruit_vc0706.py
adafruit_circuitpython_vc0706-6.0.15.dist-info/licenses/LICENSE
adafruit_circuitpython_vc0706-6.0.15.dist-info/METADATA
adafruit_circuitpython_vc0706-6.0.15.dist-info/WHEEL
adafruit_circuitpython_vc0706-6.0.15.dist-info/top_level.txt
adafruit_circuitpython_vc0706-6.0.15.dist-info/RECORD
