Metadata-Version: 2.4
Name: adafruit-circuitpython-vc0706
Version: 6.0.15
Summary: CircuitPython library for VC0706 serial TTL camera.
Author-email: Adafruit Industries <circuitpython@adafruit.com>
License: MIT
Project-URL: Homepage, https://github.com/adafruit/Adafruit_CircuitPython_VC0706
Keywords: adafruit,vc0706,serial,ttl,camera,hardware,micropython,circuitpython
Classifier: Intended Audience :: Developers
Classifier: Topic :: Software Development :: Libraries
Classifier: Topic :: Software Development :: Embedded Systems
Classifier: Topic :: System :: Hardware
Classifier: License :: OSI Approved :: MIT License
Classifier: Programming Language :: Python :: 3
License-File: LICENSE
Requires-Dist: Adafruit-Blinka
Requires-Dist: adafruit-circuitpython-busdevice
Requires-Dist: pyserial
Provides-Extra: optional
Dynamic: license-file
